flespi/__init__.py
flespi/rest.py
flespi-2.0.1.dist-info/LICENSE
flespi-2.0.1.dist-info/METADATA
flespi-2.0.1.dist-info/WHEEL
flespi-2.0.1.dist-info/top_level.txt
flespi-2.0.1.dist-info/RECORD
