Metadata-Version: 2.1
Name: flespi
Version: 2.0.1
Summary: Flespi REST API for Python
Author-email: "Golden M, Inc." <software@goldenm.com>
Maintainer-email: Kenny Mochizuki <kenny@goldenm.com>
License: MIT License
Project-URL: Repository, https://github.com/goldenm-software/flespi-python
Classifier: Programming Language :: Python :: 3
Classifier: Programming Language :: Python :: 3.10
Classifier: Programming Language :: Python :: 3.11
Classifier: Programming Language :: Python :: 3.12
Requires-Python: >=3.10
License-File: LICENSE
Requires-Dist: requests
Requires-Dist: tzdata
